.authors
.gitignore
.travis.yml
CHANGES.rst
CONTRIBUTORS
LICENSE
README.rst
distribute_setup.py
setup.cfg
setup.py
d2to1/__init__.py
d2to1/core.py
d2to1/util.py
d2to1/zestreleaser.py
d2to1.egg-info/PKG-INFO
d2to1.egg-info/SOURCES.txt
d2to1.egg-info/dependency_links.txt
d2to1.egg-info/entry_points.txt
d2to1.egg-info/not-zip-safe
d2to1.egg-info/requires.txt
d2to1.egg-info/top_level.txt
d2to1/extern/__init__.py
d2to1/extern/six.py
d2to1/tests/__init__.py
d2to1/tests/test_commands.py
d2to1/tests/test_core.py
d2to1/tests/test_hooks.py
d2to1/tests/util.py
d2to1/tests/testpackage/CHANGES.txt
d2to1/tests/testpackage/LICENSE.txt
d2to1/tests/testpackage/MANIFEST.in
d2to1/tests/testpackage/README.txt
d2to1/tests/testpackage/distribute_setup.py
d2to1/tests/testpackage/extra-file.txt
d2to1/tests/testpackage/setup.cfg
d2to1/tests/testpackage/setup.py
d2to1/tests/testpackage/d2to1_testpackage/__init__.py
d2to1/tests/testpackage/d2to1_testpackage/_setup_hooks.py
d2to1/tests/testpackage/d2to1_testpackage/package_data/1.txt
d2to1/tests/testpackage/d2to1_testpackage/package_data/2.txt
d2to1/tests/testpackage/data_files/a.txt
d2to1/tests/testpackage/data_files/b.txt
d2to1/tests/testpackage/data_files/c.rst
d2to1/tests/testpackage/src/testext.c