Metadata-Version: 1.1
Name: d2to1
Version: 0.2.10
Summary: Allows using distutils2-like setup.cfg files for a package's metadata
Home-page: http://pypi.python.org/pypi/d2to1
Author: Erik M. Bray
Author-email: embray@stsci.edu
License: UNKNOWN
Platform: UNKNOWN
Classifier: Development Status :: 5 - Production/Stable
Classifier: Environment :: Plugins
Classifier: Framework :: Setuptools Plugin
Classifier: Intended Audience :: Developers
Classifier: License :: OSI Approved :: BSD License
Classifier: Operating System :: OS Independent
Classifier: Programming Language :: Python
Classifier: Programming Language :: Python :: 3
Classifier: Topic :: Software Development :: Build Tools
Classifier: Topic :: Software Development :: Libraries :: Python Modules
Classifier: Topic :: System :: Archiving :: Packaging
